duckdb_sqlalchemy/__init__.py
duckdb_sqlalchemy/_supports.py
duckdb_sqlalchemy/bulk.py
duckdb_sqlalchemy/capabilities.py
duckdb_sqlalchemy/config.py
duckdb_sqlalchemy/conftest.py
duckdb_sqlalchemy/datatypes.py
duckdb_sqlalchemy/motherduck.py
duckdb_sqlalchemy/olap.py
duckdb_sqlalchemy/py.typed
duckdb_sqlalchemy/requirements.py
duckdb_sqlalchemy/url.py
duckdb_sqlalchemy/tests/__init__.py
duckdb_sqlalchemy/tests/conftest.py
duckdb_sqlalchemy/tests/test_basic.py
duckdb_sqlalchemy/tests/test_core_units.py
duckdb_sqlalchemy/tests/test_datatypes.py
duckdb_sqlalchemy/tests/test_execution_options.py
duckdb_sqlalchemy/tests/test_helpers.py
duckdb_sqlalchemy/tests/test_integration.py
duckdb_sqlalchemy/tests/test_pandas.py
duckdb_sqlalchemy/tests/test_pyarrow.py
duckdb_sqlalchemy/tests/util.py
duckdb_sqlalchemy/tests/snapshots/test_datatypes/test_interval/schema.sql
duckdb_sqlalchemy/tests/sqlalchemy_suite/conftest.py
duckdb_sqlalchemy/tests/sqlalchemy_suite/test_suite.py
duckdb_sqlalchemy-1.4.3.dist-info/METADATA
duckdb_sqlalchemy-1.4.3.dist-info/WHEEL
duckdb_sqlalchemy-1.4.3.dist-info/entry_points.txt
duckdb_sqlalchemy-1.4.3.dist-info/licenses/LICENSE.txt
duckdb_sqlalchemy-1.4.3.dist-info/RECORD
