Metadata-Version: 2.4
Name: duckdb-sqlalchemy
Version: 1.4.3
Summary: DuckDB SQLAlchemy dialect for DuckDB and MotherDuck
Project-URL: Bug Tracker, https://github.com/leonardovida/duckdb-sqlalchemy/issues
Project-URL: Changelog, https://github.com/leonardovida/duckdb-sqlalchemy/releases
Project-URL: Documentation, https://leonardovida.github.io/duckdb-sqlalchemy/
Project-URL: repository, https://github.com/leonardovida/duckdb-sqlalchemy
Project-URL: Upstream, https://github.com/Mause/duckdb_engine
Author-email: Leonardo Vida <lleonardovida@gmail.com>
License-Expression: MIT
License-File: LICENSE.txt
Keywords: analytics,database,dialect,duckdb,motherduck,olap,sqlalchemy
Classifier: Development Status :: 5 - Production/Stable
Classifier: Intended Audience :: Developers
Classifier: License :: OSI Approved :: MIT License
Classifier: Programming Language :: Python :: 3
Classifier: Programming Language :: Python :: 3 :: Only
Classifier: Programming Language :: Python :: 3.9
Classifier: Programming Language :: Python :: 3.10
Classifier: Programming Language :: Python :: 3.11
Classifier: Programming Language :: Python :: 3.12
Classifier: Programming Language :: Python :: 3.13
Classifier: Programming Language :: Python :: 3.14
Classifier: Topic :: Database
Classifier: Topic :: Database :: Front-Ends
Requires-Python: <4,>=3.9
Requires-Dist: duckdb>=0.5.0
Requires-Dist: packaging>=21
Requires-Dist: sqlalchemy>=1.3.22
Provides-Extra: dev
Requires-Dist: fsspec<2026.0.0,>=2025.2.0; extra == 'dev'
Requires-Dist: github-action-utils<2.0.0,>=1.1.0; extra == 'dev'
Requires-Dist: hypothesis<7.0.0,>=6.75.2; extra == 'dev'
Requires-Dist: jupysql<0.12.0,>=0.11.1; extra == 'dev'
Requires-Dist: numpy<2.0,>=1.24; (python_version < '3.12') and extra == 'dev'
Requires-Dist: numpy<3.0,>=1.26; (python_version >= '3.12' and python_version < '3.13') and extra == 'dev'
Requires-Dist: numpy<3.0,>=2.0; (python_version >= '3.13') and extra == 'dev'
Requires-Dist: pandas<2.0,>=1; (python_version < '3.12') and extra == 'dev'
Requires-Dist: pandas<3.0,>=2.2; (python_version >= '3.12') and extra == 'dev'
Requires-Dist: pyarrow>=22.0.0; (python_version >= '3.10') and extra == 'dev'
Requires-Dist: pytest-cov<6.0.0,>=5.0.0; extra == 'dev'
Requires-Dist: pytest-remotedata<0.5.0,>=0.4.0; extra == 'dev'
Requires-Dist: pytest-snapshot<1.0.0,>=0.9.0; extra == 'dev'
Requires-Dist: pytest<9.0.0,>=8.0.0; extra == 'dev'
Requires-Dist: toml<0.11.0,>=0.10.2; extra == 'dev'
Requires-Dist: ty; extra == 'dev'
Provides-Extra: devtools
Requires-Dist: pdbpp<0.12.0,>=0.11.0; extra == 'devtools'
Requires-Dist: pre-commit>=4.0.0; (python_version >= '3.9') and extra == 'devtools'
